vats_proxy/__init__.py
vats_proxy/retrieve_proxy.py
vats_proxy-0.8.1.dist-info/METADATA
vats_proxy-0.8.1.dist-info/WHEEL
vats_proxy-0.8.1.dist-info/top_level.txt
vats_proxy-0.8.1.dist-info/RECORD
