Metadata-Version: 2.1
Name: vats-proxy
Version: 0.8.1
Summary: Free Proxy Library for requests library
Home-page: 
Author: Goktug Cetin
Author-email: goktugcetin1@gmail.com
License: MIT
Platform: UNKNOWN
Classifier: Intended Audience :: Developers
Classifier: License :: OSI Approved :: MIT License
Classifier: Programming Language :: Python
Classifier: Programming Language :: Python :: 3
Classifier: Programming Language :: Python :: 3.6
Classifier: Programming Language :: Python :: 3.7
Classifier: Programming Language :: Python :: 3.8
Classifier: Programming Language :: Python :: 3.9
Classifier: Operating System :: OS Independent
Requires-Dist: requests
Requires-Dist: free-proxy
